pandas_explo/__init__.py
pandas_explo/core.py
mon_pandas_explo_unique_123-0.0.2.dist-info/METADATA
mon_pandas_explo_unique_123-0.0.2.dist-info/WHEEL
mon_pandas_explo_unique_123-0.0.2.dist-info/top_level.txt
mon_pandas_explo_unique_123-0.0.2.dist-info/RECORD
