Metadata-Version: 2.4
Name: mon-pandas-explo-unique-123
Version: 0.0.2
Summary: Mon outil d'analyse de DataFrame
Author: yasserxkamal
License: MIT
Requires-Python: >=3.7
Requires-Dist: pandas
Requires-Dist: ipython
